nanuquant/__init__.py
nanuquant/_version.py
nanuquant/config.py
nanuquant/exceptions.py
nanuquant/namespace.py
nanuquant/py.typed
nanuquant/types.py
nanuquant/advanced/__init__.py
nanuquant/advanced/trades.py
nanuquant/core/__init__.py
nanuquant/core/distribution.py
nanuquant/core/performance.py
nanuquant/core/periods.py
nanuquant/core/returns.py
nanuquant/core/risk.py
nanuquant/core/rolling.py
nanuquant/core/timeseries.py
nanuquant/core/utils.py
nanuquant/core/validation.py
nanuquant/institutional/__init__.py
nanuquant/institutional/_helpers.py
nanuquant/institutional/execution.py
nanuquant/institutional/portfolio.py
nanuquant/institutional/robustness.py
nanuquant/institutional/systemic.py
nanuquant/institutional/var_extensions.py
nanuquant/institutional/volatility.py
nanuquant/reports/__init__.py
nanuquant/reports/html.py
nanuquant/reports/metrics.py
nanuquant/trades/__init__.py
nanuquant/trades/config.py
nanuquant/trades/conversion.py
nanuquant/trades/equity.py
nanuquant/trades/types.py
nanuquant/trades/utils.py
nanuquant/trades/validation.py
nanuquant-0.1.0.dist-info/METADATA
nanuquant-0.1.0.dist-info/WHEEL
nanuquant-0.1.0.dist-info/licenses/LICENSE
nanuquant-0.1.0.dist-info/RECORD
