Metadata-Version: 2.4
Name: nanuquant
Version: 0.1.0
Summary: Institutional quantitative analytics at Polars speed.
Project-URL: Homepage, https://github.com/launchstack-dev/nanuquant
Project-URL: Repository, https://github.com/launchstack-dev/nanuquant
Project-URL: Changelog, https://github.com/launchstack-dev/nanuquant/blob/main/CHANGELOG.md
Project-URL: Issues, https://github.com/launchstack-dev/nanuquant/issues
Author: Trade Conductor
License-Expression: MIT
License-File: LICENSE
Keywords: backtesting,garch,institutional-metrics,polars,quantitative-finance,risk-management,trading
Classifier: Development Status :: 3 - Alpha
Classifier: Intended Audience :: Financial and Insurance Industry
Classifier: Topic :: Office/Business :: Financial :: Investment
Classifier: Topic :: Scientific/Engineering :: Information Analysis
Classifier: Typing :: Typed
Requires-Python: >=3.10
Requires-Dist: numpy>=1.24
Requires-Dist: polars>=0.20.0
Requires-Dist: scipy>=1.10.0
Provides-Extra: all
Requires-Dist: msgspec>=0.18; extra == 'all'
Requires-Dist: mypy>=1.8; extra == 'all'
Requires-Dist: numpy>=1.24; extra == 'all'
Requires-Dist: pandas>=2.0; extra == 'all'
Requires-Dist: pyarrow>=14.0; extra == 'all'
Requires-Dist: pytest-benchmark>=4.0; extra == 'all'
Requires-Dist: pytest>=8.0; extra == 'all'
Requires-Dist: quantstats-lumi>=0.3; extra == 'all'
Requires-Dist: yfinance>=0.2.40; extra == 'all'
Provides-Extra: dev
Requires-Dist: mypy>=1.8; extra == 'dev'
Requires-Dist: numpy>=1.24; extra == 'dev'
Requires-Dist: pandas>=2.0; extra == 'dev'
Requires-Dist: pyarrow>=14.0; extra == 'dev'
Requires-Dist: pytest-benchmark>=4.0; extra == 'dev'
Requires-Dist: pytest>=8.0; extra == 'dev'
Requires-Dist: quantstats-lumi>=0.3; extra == 'dev'
Requires-Dist: yfinance>=0.2.40; extra == 'dev'
Provides-Extra: reports
Requires-Dist: msgspec>=0.18; extra == 'reports'
